odoo/addons/stock_quant_history/README.rst
odoo/addons/stock_quant_history/__init__.py
odoo/addons/stock_quant_history/__manifest__.py
odoo/addons/stock_quant_history/i18n/fr.po
odoo/addons/stock_quant_history/i18n/it.po
odoo/addons/stock_quant_history/i18n/stock_quant_history.pot
odoo/addons/stock_quant_history/models/__init__.py
odoo/addons/stock_quant_history/models/res_company.py
odoo/addons/stock_quant_history/models/res_config_settings.py
odoo/addons/stock_quant_history/models/stock_picking.py
odoo/addons/stock_quant_history/models/stock_quant_history.py
odoo/addons/stock_quant_history/models/stock_quant_history_snapshot.py
odoo/addons/stock_quant_history/readme/CONSTRIBUTORS.rst
odoo/addons/stock_quant_history/readme/DESCRIPTION.rst
odoo/addons/stock_quant_history/readme/ROADMAP.rst
odoo/addons/stock_quant_history/readme/USAGE.rst
odoo/addons/stock_quant_history/security/ir.model.access.csv
odoo/addons/stock_quant_history/static/description/icon.png
odoo/addons/stock_quant_history/static/description/index.html
odoo/addons/stock_quant_history/tests/__init__.py
odoo/addons/stock_quant_history/tests/common.py
odoo/addons/stock_quant_history/tests/test_stock_picking.py
odoo/addons/stock_quant_history/tests/test_stock_quant_history.py
odoo/addons/stock_quant_history/views/res_config_settings_views.xml
odoo/addons/stock_quant_history/views/stock-quant-history-snapshot.xml
odoo/addons/stock_quant_history/views/stock-quant-history.xml
odoo14_addon_stock_quant_history-14.0.1.3.0.dist-info/METADATA
odoo14_addon_stock_quant_history-14.0.1.3.0.dist-info/WHEEL
odoo14_addon_stock_quant_history-14.0.1.3.0.dist-info/top_level.txt
odoo14_addon_stock_quant_history-14.0.1.3.0.dist-info/RECORD
