Metadata-Version: 2.1
Name: odoo14-addon-stock_quant_history
Version: 14.0.1.3.0
Summary: Re-generate stock quants for given date
Home-page: https://github.com/OCA/stock-logistics-reporting
Author: Pierre Verkest <pierreverkest84@gmail.com>, Stéphane Mangin <stephane.mangin@foodles.com>, Odoo Community Association (OCA)
Author-email: support@odoo-community.org
License: AGPL-3
Classifier: Programming Language :: Python
Classifier: Framework :: Odoo
Classifier: Framework :: Odoo :: 14.0
Classifier: License :: OSI Approved :: GNU Affero General Public License v3
Requires-Python: >=3.6
Requires-Dist: odoo<14.1dev,>=14.0a
